sdo/__init__.py
solar_dynamics_observatory-0.0.1.dist-info/METADATA
solar_dynamics_observatory-0.0.1.dist-info/WHEEL
solar_dynamics_observatory-0.0.1.dist-info/top_level.txt
solar_dynamics_observatory-0.0.1.dist-info/RECORD
